pulumi_aws_tags/__init__.py
pulumi_aws_tags/autotag.py
pulumi_aws_tags/py.typed
pulumi_aws_tags/taggable.py
pulumi_aws_tags-3.0.0.dist-info/METADATA
pulumi_aws_tags-3.0.0.dist-info/WHEEL
pulumi_aws_tags-3.0.0.dist-info/RECORD
