Metadata-Version: 2.4
Name: pulumi_aws_tags
Version: 3.0.0
Summary: Pulumi package that helps manage tags for AWS resources
Project-URL: Homepage, https://github.com/tlinhart/pulumi-aws-tags
Author-email: Tomáš Linhart <pasmen@gmail.com>
License-Expression: MIT
Keywords: aws,pulumi,tags
Classifier: Operating System :: OS Independent
Classifier: Programming Language :: Python :: 3
Requires-Python: >=3.10
Requires-Dist: pulumi-aws<8.0.0,>=4.0.0
Requires-Dist: pulumi<4.0.0,>=3.118.0
